entanglement_forging/__init__.py
entanglement_forging/core/__init__.py
entanglement_forging/core/cholesky_hamiltonian.py
entanglement_forging/core/classical_energies.py
entanglement_forging/core/entanglement_forged_config.py
entanglement_forging/core/forged_operator.py
entanglement_forging/core/orbitals_to_reduce.py
entanglement_forging/core/wrappers/__init__.py
entanglement_forging/core/wrappers/entanglement_forged_driver.py
entanglement_forging/core/wrappers/entanglement_forged_ground_state_eigensolver.py
entanglement_forging/core/wrappers/entanglement_forged_vqe.py
entanglement_forging/core/wrappers/entanglement_forged_vqe_result.py
entanglement_forging/utils/__init__.py
entanglement_forging/utils/bootstrap_result.py
entanglement_forging/utils/combined_result.py
entanglement_forging/utils/copysample_circuits.py
entanglement_forging/utils/forging_subroutines.py
entanglement_forging/utils/generic_execution_subroutines.py
entanglement_forging/utils/log.py
entanglement_forging/utils/meas_mit_filters_faster.py
entanglement_forging/utils/meas_mit_fitters_faster.py
entanglement_forging/utils/prepare_bitstring.py
entanglement_forging/utils/pseudorichardson.py
entanglement_forging/utils/legacy/__init__.py
entanglement_forging/utils/legacy/base_operator.py
entanglement_forging/utils/legacy/common.py
entanglement_forging/utils/legacy/op_converter.py
entanglement_forging/utils/legacy/pauli_graph.py
entanglement_forging/utils/legacy/tpb_grouped_weighted_pauli_operator.py
entanglement_forging/utils/legacy/weighted_pauli_operator.py
tests/__init__.py
tests/unit_tests/__init__.py
tests/unit_tests/test_orbitals_to_reduce.py
tests/wrappers/__init__.py
tests/wrappers/test_entanglement_forged_ground_state_eigensolver.py
entanglement_forging-0.2.1.dist-info/LICENSE.txt
entanglement_forging-0.2.1.dist-info/METADATA
entanglement_forging-0.2.1.dist-info/WHEEL
entanglement_forging-0.2.1.dist-info/top_level.txt
entanglement_forging-0.2.1.dist-info/RECORD
